m3u8_getpack/__init__.py
m3u8_getpack/__main__.py
m3u8_getpack/core.py
m3u8_getpack/downloader.py
m3u8_getpack/fileman.py
m3u8_getpack/merger.py
m3u8_getpack/notifier.py
m3u8_getpack/parser.py
m3u8_getpack/utils.py
m3u8_getpack-0.0.3.dist-info/licenses/LICENSE
m3u8_getpack-0.0.3.dist-info/METADATA
m3u8_getpack-0.0.3.dist-info/WHEEL
m3u8_getpack-0.0.3.dist-info/entry_points.txt
m3u8_getpack-0.0.3.dist-info/top_level.txt
m3u8_getpack-0.0.3.dist-info/RECORD
