Metadata-Version: 2.4
Name: m3u8-getpack
Version: 0.0.3
Summary: A command-line tool for downloading and merging m3u8 .ts video segments into a single MP4 file.
Author: Fabio Castro Dias
License: MIT License
Project-URL: Homepage, https://github.com/fabiocastrodias/m3u8-getpack
Requires-Python: >=3.10
License-File: LICENSE
Requires-Dist: ffmpeg-python>=0.2.0
Requires-Dist: future>=1.0.0
Requires-Dist: wget>=3.2
Dynamic: license-file
